embeddingdb/__init__.py
embeddingdb/__main__.py
embeddingdb/cli.py
embeddingdb/constants.py
embeddingdb/version.py
embeddingdb/sql/__init__.py
embeddingdb/sql/analysis.py
embeddingdb/sql/io.py
embeddingdb/sql/models.py
embeddingdb/web/__init__.py
embeddingdb/web/__main__.py
embeddingdb/web/api.py
embeddingdb/web/app.py
embeddingdb/web/ext.py
embeddingdb/web/wsgi.py
embeddingdb-0.0.1.dist-info/LICENSE
embeddingdb-0.0.1.dist-info/METADATA
embeddingdb-0.0.1.dist-info/WHEEL
embeddingdb-0.0.1.dist-info/entry_points.txt
embeddingdb-0.0.1.dist-info/top_level.txt
embeddingdb-0.0.1.dist-info/RECORD
