Metadata-Version: 2.1
Name: embeddingdb
Version: 0.0.1
Summary: A package for storing and querying knowledge graph embeddings
Home-page: UNKNOWN
License: MIT
Keywords: Knowledge Graph Embeddings,Machine Learning,Data Mining,Linked Data
Platform: UNKNOWN
Classifier: Environment :: Console
Classifier: Intended Audience :: Science/Research
Classifier: License :: OSI Approved :: MIT License
Classifier: Operating System :: OS Independent
Classifier: Programming Language :: Python
Classifier: Programming Language :: Python :: 3.6
Classifier: Programming Language :: Python :: 3.7
Classifier: Programming Language :: Python :: 3 :: Only
Classifier: Topic :: Scientific/Engineering :: Artificial Intelligence
Classifier: Topic :: Scientific/Engineering :: Chemistry
Classifier: Topic :: Scientific/Engineering :: Bio-Informatics
Classifier: Topic :: Scientific/Engineering :: Mathematics
Classifier: Topic :: Scientific/Engineering :: Information Analysis
Requires-Python: >=3.7
Requires-Dist: sqlalchemy
Requires-Dist: tqdm
Requires-Dist: psycopg2-binary
Requires-Dist: scikit-learn
Requires-Dist: click
Requires-Dist: easy-config
Requires-Dist: pandas
Requires-Dist: joblib
Provides-Extra: docs
Requires-Dist: sphinx ; extra == 'docs'
Requires-Dist: sphinx-rtd-theme ; extra == 'docs'
Requires-Dist: sphinx-click ; extra == 'docs'
Requires-Dist: sphinx-autodoc-typehints ; extra == 'docs'
Provides-Extra: web
Requires-Dist: flask ; extra == 'web'
Requires-Dist: flask-bootstrap ; extra == 'web'
Requires-Dist: flask-sqlalchemy ; extra == 'web'
Requires-Dist: flasgger ; extra == 'web'
